<search>Marvel's The Punisher</search><url>https://trakt.tv/shows/marvel-s-the-punisher</url><posterURL>https://walter.trakt.tv/images/shows/000/112/663/posters/thumb/ca54615d2a.jpg</posterURL><genres>Adventure, Action, Drama, Crime, </genres><plot>After the murder of his family, Marine veteran Frank Castle became a vigilante known as 'The Punisher' with only one goal in mind – to avenge them. With his revenge now complellte, Frank's war-time past comes back to haunt him.</plot><image>\graphics\tv-show-logos\marvels the punisher.png</image><searchInFolder>D:/Downloads</searchInFolder><moveToFolder>D:\media\tv\marvels the punisher</moveToFolder><searchFor>marvels the punisher</searchFor>
<S01E01>true</S01E01><release>2017-11-17</release>
<S01E02>true</S01E02><release>2017-11-17</release>
<S01E03>true</S01E03><release>2017-11-17</release>
<S01E04>true</S01E04><release>2017-11-17</release>
<S01E05>true</S01E05><release>2017-11-17</release>
<S01E06>true</S01E06><release>2017-11-17</release>
<S01E07>true</S01E07><release>2017-11-17</release>
<S01E08>true</S01E08><release>2017-11-17</release>
<S01E09>true</S01E09><release>2017-11-17</release>
<S01E10>true</S01E10><release>2017-11-17</release>
<S01E11>true</S01E11><release>2017-11-17</release>
<S01E12>true</S01E12><release>2017-11-17</release>
<S01E13>true</S01E13><release>2017-11-17</release>
