<search>Rick and Morty</search><url>https://trakt.tv/shows/rick-and-morty</url><posterURL>https://walter.trakt.tv/images/shows/000/069/829/posters/thumb/16434b4797.jpg</posterURL><genres>Science Fiction, Fantasy, Action, Adventure, Comedy, Animation, </genres><plot>An animated series that follows the misadventures of an alcoholic scientist Rick and his overly nervous grandson Morty, who split their time between domestic family life and intergalactic travel. Often finding themselves in a heap of trouble that more often than not is created through their own actions.</plot><image>\graphics\tv-show-logos\rick and morty.png</image><searchInFolder>C:/Users/taibhse/Downloads</searchInFolder><moveToFolder>D:\media\tv\Rick and Morty</moveToFolder><searchFor>rick and morty</searchFor>
<S01E01>true</S01E01><release>2013-12-03</release>
<S01E02>true</S01E02><release>2013-12-10</release>
<S01E03>true</S01E03><release>2013-12-17</release>
<S01E04>true</S01E04><release>2014-01-14</release>
<S01E05>true</S01E05><release>2014-01-21</release>
<S01E06>true</S01E06><release>2014-01-28</release>
<S01E07>true</S01E07><release>2014-03-11</release>
<S01E08>true</S01E08><release>2014-03-18</release>
<S01E09>true</S01E09><release>2014-03-25</release>
<S01E10>true</S01E10><release>2014-04-08</release>
<S01E11>true</S01E11><release>2014-04-15</release>
<S02E01>true</S02E01><release>2015-07-27</release>
<S02E02>true</S02E02><release>2015-08-03</release>
<S02E03>true</S02E03><release>2015-08-10</release>
<S02E04>true</S02E04><release>2015-08-17</release>
<S02E05>true</S02E05><release>2015-08-24</release>
<S02E06>true</S02E06><release>2015-08-31</release>
<S02E07>true</S02E07><release>2015-09-14</release>
<S02E08>true</S02E08><release>2015-09-21</release>
<S02E09>true</S02E09><release>2015-09-28</release>
<S02E10>true</S02E10><release>2015-10-05</release>
<S03E01>true</S03E01><release>2017-04-02</release>
<S03E02>true</S03E02><release>2017-07-31</release>
<S03E03>true</S03E03><release>2017-08-07</release>
<S03E04>true</S03E04><release>2017-08-14</release>
<S03E05>true</S03E05><release>2017-08-21</release>
<S03E06>true</S03E06><release>2017-08-28</release>
<S03E07>true</S03E07><release>2017-09-11</release>
<S03E08>true</S03E08><release>2017-09-18</release>
<S03E09>true</S03E09><release>2017-09-25</release>
<S03E10>true</S03E10><release>2017-10-02</release>
<S04E01>false</S04E01><release></release>
